header_creator/__init__.py
header_creator/cli.py
header_creator/config.py
header_creator/core.py
header_creator/header_processor.py
header_creator/image_generator.py
header_creator-0.2.2.dist-info/LICENSE
header_creator-0.2.2.dist-info/METADATA
header_creator-0.2.2.dist-info/WHEEL
header_creator-0.2.2.dist-info/entry_points.txt
header_creator-0.2.2.dist-info/top_level.txt
header_creator-0.2.2.dist-info/RECORD
