Metadata-Version: 2.1
Name: header-creator
Version: 0.2.2
Summary: A package to create header images using Ideogram API
Home-page: https://github.com/Sunwood-ai-labs/header_creator
Author: Sunwood-ai-labs
Author-email: your.email@example.com
Classifier: Development Status :: 3 - Alpha
Classifier: Intended Audience :: Developers
Classifier: License :: OSI Approved :: MIT License
Classifier: Operating System :: OS Independent
Classifier: Programming Language :: Python :: 3
Classifier: Programming Language :: Python :: 3.7
Classifier: Programming Language :: Python :: 3.8
Classifier: Programming Language :: Python :: 3.9
Classifier: Programming Language :: Python :: 3.10
Requires-Python: >=3.7
License-File: LICENSE
Requires-Dist: requests
Requires-Dist: python-dotenv
Requires-Dist: loguru
Requires-Dist: click
Requires-Dist: pic-to-header
